hyperp/__init__.py
hyperp/download.py
hyperp/is_float.py
hyperp/is_int.py
hyperp/is_ip4.py
hyperp/mkdir.py
hyperp/mkdir_file.py
hyperp/read.py
hyperp/rmdir.py
hyperp/sanitize.py
hyperp/send_file.py
hyperp/throttle_call.py
hyperp/timer.py
hyperp/to_int.py
hyperp/write.py
hyperp/django/__init__.py
hyperp/django/cache.py
hyperp/django/get_csrf.py
hyperp/django/get_ip.py
hyperp-1.0.15.dist-info/METADATA
hyperp-1.0.15.dist-info/WHEEL
hyperp-1.0.15.dist-info/top_level.txt
hyperp-1.0.15.dist-info/zip-safe
hyperp-1.0.15.dist-info/RECORD
