Metadata-Version: 2.4
Name: hyperp
Version: 1.0.15
Summary: Hyper charge your productivity
Home-page: https://github.com/yourusername/your-repo-name
Author: Martin Baun
Author-email: nospam@gmail.com
Classifier: Programming Language :: Python :: 3
Classifier: License :: OSI Approved :: MIT License
Classifier: Operating System :: OS Independent
Requires-Python: >=3.10
Requires-Dist: requests>=2.28.0
Requires-Dist: docopt>=0.6.2
Requires-Dist: cryptography>=41.0.2
Dynamic: author
Dynamic: author-email
Dynamic: classifier
Dynamic: description
Dynamic: description-content-type
Dynamic: home-page
Dynamic: requires-python
Dynamic: summary
